setup.py
hahahaha_distributions/Binomialdistribution.py
hahahaha_distributions/Gaussiandistribution.py
hahahaha_distributions/Generaldistribution.py
hahahaha_distributions/__init__.py
hahahaha_distributions.egg-info/PKG-INFO
hahahaha_distributions.egg-info/SOURCES.txt
hahahaha_distributions.egg-info/dependency_links.txt
hahahaha_distributions.egg-info/not-zip-safe
hahahaha_distributions.egg-info/top_level.txt